{
  "price" : "money",
  "production" : "percentage",
  "ibk" : "money",
  "mkt" : "money",
  "id" : "money",
  "survey" : "money",
  "design" : "money",
  "new_debt" : "money",
  "average_production" : "percentage",
  "risk_slope" : "number",
  "risk_score" : "number",
  "risk_level" : "number",
  "event_prob" : "percentage",
  "ppe" : "money",
  "ppe_industry" : "money",
  "cbu" : "money",
  "average_cbu" : "money",
  "max_u" : "units",
  "max_u_industry" : "units",
  "u_prod" : "units",
  "output" : "money",
  "worker_productivity" : "number",
  "offered_u" : "units",
  "max_w" : "number",
  "employees" : "units",
  "employees_industry" : "number",
  "revenue_employees" : "money",
  "sold_u_employees" : "units",
  "vpe" : "money",
  "target" : "money",
  "target_industry" : "money",
  "share_target" : "ratio",
  "delta_employees" : "number",
  "output_industry" : "money",
  "added_offer" : "money",
  "price_sum" : "money",
  "average_price" : "money",
  "annual_rounds" : "number",
  "current_stock_industry" : "units",
  "price_change" : "money",
  "depreciation" : "money",
  "capex" : "money",
  "ppe_next" : "money",
  "u_prod_industry" : "units",
  "active_id" : "money",
  "active_id_industry" : "money",
  "active_investements" : "money",
  "pond_share_id" : "ratio",
  "id_index" : "number",
  "id_index_industry" : "number",
  "final_id_points" : "number",
  "corrected_price" : "money",
  "max_corrected_price" : "money",
  "price_index_user" : "number",
  "price_index_industry" : "number",
  "active_mkt" : "money",
  "active_mkt_industry" : "money",
  "active_mkt_share" : "ratio",
  "delta_mkt_share" : "number",
  "mkt_index" : "number",
  "mkt_index_industry" : "number",
  "final_price_points" : "number",
  "final_mkt_points" : "number",
  "total_points_player" : "number",
  "total_points_industry" : "number",
  "delta_interest_rate" : "percentage",
  "pms" : "ratio",
  "added_demand" : "money",
  "real_added_demand" : "percentage",
  "pda" : "number",
  "poa" : "number",
  "u_dem_industry" : "units",
  "eoa" : "number",
  "demand_u" : "units",
  "offer_surplus" : "units",
  "sold_u" : "units",
  "sold_u_industry" : "units",
  "market_share" : "percentage",
  "current_stock" : "units",
  "final_stock" : "units",
  "final_stock_industry" : "units",
  "inventories" : "money",
  "inventories_industry" : "money",
  "stock_share" : "percentage",
  "inventory_change" : "money",
  "pipeline_status" : "percentage",
  "stock_variation_u" : "units",
  "offered_u_industry" : "units",
  "demand_surplus" : "percentage",
  "salaries_expense" : "money",
  "total_revenue" : "money",
  "total_revenue_industry" : "money",
  "cost_sold_goods" : "money",
  "gross_profit" : "money",
  "top_limit" : "number",
  "event_cost" : "money",
  "subsidy" : "money",
  "financial_debt" : "money",
  "financial_result" : "money",
  "break_even" : "units",
  "total_cost_u" : "money",
  "margin_u" : "money",
  "ebitda" : "money",
  "ebit" : "money",
  "uai" : "money",
  "profit_tax_amount" : "money",
  "vat_tax_amount" : "money",
  "other_tax_amount" : "money",
  "labour_tax" : "money",
  "taxes" : "money",
  "average_payed_taxes" : "money",
  "un" : "money",
  "retained_earnings" : "money",
  "growth_rate" : "percentage",
  "company_ranking" : "number",
  "company_ranking_delta" : "number",
  "opening_cash" : "money",
  "final_cash" : "money",
  "financial_inv" : "money",
  "current_assets" : "money",
  "non_current_assets" : "money",
  "total_assets" : "money",
  "fix_assets" : "money",
  "net_assets" : "money",
  "non_current_liabilities" : "money",
  "current_liabilities" : "money",
  "liabilities" : "money",
  "shareholders_equity" : "money",
  "equity" : "money",
  "total_equity" : "money",
  "out_zone" : "percentage",
  "loan_ratio" : "ratio",
  "top_loan" : "money",
  "total_funds" : "money",
  "total_funds_ratio" : "percentage",
  "asset_indebtedness" : "ratio",
  "equity_indebtedness" : "ratio",
  "fix_assets_indebtedness" : "ratio",
  "demand_change" : "units",
  "demand_elasticity" : "ratio",
  "fix_asset_rotation" : "ratio",
  "total_asset_rotation" : "ratio",
  "financial_impact" : "percentage",
  "asset_net_profitability" : "percentage",
  "gross_profitability" : "percentage",
  "sales_net_profitability" : "percentage",
  "roe" : "percentage",
  "roa" : "percentage",
  "risk_free_output" : "money",
  "risk_cost" : "money",
  "sd_price" : "number",
  "necesary_funds" : "money",
  "salary" : "money",
  "hirschman_index" : "number",
  "min_funds" : "money",
  "easy_business_score_tax" : "percentage",
  "financial_cost" : "percentage",
  "initial_eq" : "percentage",
  "interest_rate" : "percentage",
  "labor_tax" : "percentage",
  "pofit_tax" : "percentage",
  "risk_limit_max" : "percentage",
  "risk_limit_min" : "percentage",
  "vat_tax" : "percentage",
  "profit_tax" : "percentage",
  "unrealized_sales": "money",
  "archivied_target" : "percentage",
  "average_total_cost": "money",
  "total_cost_sum": "money",
  "total_cost": "money", 
  "offer_ratio": "percentage",
  "reference_cost" : "money",
  "taxes_sum": "money",
  "achieved_target": "percentage",
  "opening_cash_ratio" : "ratio",
  "line_credit" : "money",
  "best_price" : "money",
  "industry_pipeline" : "percentage",
  "positive_top_limit" : "number",
  "positive_trigger" : "number",
  "lucky_player" : "number",
  "success_id" : "number",
  "strength" : "number",
  "decision_success" : "text",
  "avg_sales" : "percentage",
  "avg_total_cost" : "money",
  "salaries_budget" : "money",
  "mkt_budget" : "money",
  "mkt_industry" : "money",
  "ibk_industry" : "money",
  "id_budget" : "money",
  "id_industry" : "money",
  "corrected_demand" : "units",
  "total_cost_industry" : "money",
  "dry_liquity" : "money",
  "earnings" : "money",
  "max_e" : "units",
  "status_company" : "text"
}